gridgraphresearch/ConfigFileManager.py
gridgraphresearch/GridLfstanalyzer.py
gridgraphresearch/__init__.py
gridgraphresearch-0.1.0.dist-info/licenses/LICENSE
gridgraphresearch-0.1.0.dist-info/METADATA
gridgraphresearch-0.1.0.dist-info/WHEEL
gridgraphresearch-0.1.0.dist-info/top_level.txt
gridgraphresearch-0.1.0.dist-info/RECORD
