Metadata-Version: 2.4
Name: gridgraphresearch
Version: 0.1.0
Summary: Power System Load Flow and Transient Stability Analysis Tool
Author: pronoobe
License: MIT
Project-URL: Homepage, https://github.com/pronoobe/GridGraphResearch
Project-URL: Bug Tracker, https://github.com/pronoobe/GridGraphResearch/issues
Keywords: power system,load flow,transient stability,grid analysis,electrical engineering
Classifier: Development Status :: 3 - Alpha
Classifier: Intended Audience :: Science/Research
Classifier: Intended Audience :: Developers
Classifier: License :: OSI Approved :: MIT License
Classifier: Operating System :: Microsoft :: Windows
Classifier: Programming Language :: Python :: 3
Classifier: Programming Language :: Python :: 3.7
Classifier: Programming Language :: Python :: 3.8
Classifier: Programming Language :: Python :: 3.9
Classifier: Programming Language :: Python :: 3.10
Classifier: Programming Language :: Python :: 3.11
Classifier: Programming Language :: Python :: 3.12
Classifier: Topic :: Scientific/Engineering
Classifier: Topic :: Scientific/Engineering :: Physics
Requires-Python: >=3.7
License-File: LICENSE
Provides-Extra: graph
Requires-Dist: networkx; extra == "graph"
Requires-Dist: matplotlib; extra == "graph"
Provides-Extra: dev
Requires-Dist: pytest; extra == "dev"
Requires-Dist: pytest-cov; extra == "dev"
Provides-Extra: all
Requires-Dist: networkx; extra == "all"
Requires-Dist: matplotlib; extra == "all"
Requires-Dist: pytest; extra == "all"
Requires-Dist: pytest-cov; extra == "all"
Dynamic: license-file
